ebook_convert_helper/__init__.py
ebook_convert_helper/cli.py
ebook_convert_helper-0.3.2.dist-info/LICENSE.txt
ebook_convert_helper-0.3.2.dist-info/METADATA
ebook_convert_helper-0.3.2.dist-info/WHEEL
ebook_convert_helper-0.3.2.dist-info/entry_points.txt
ebook_convert_helper-0.3.2.dist-info/top_level.txt
ebook_convert_helper-0.3.2.dist-info/RECORD
