Metadata-Version: 2.1
Name: ebook-convert-helper
Version: 0.3.2
Summary: A helper cli for calibre's ebook-convert CLI which is used to convert all files in an directory into another format.
Home-page: https://github.com/arzkar/calibre-ebook-convert-helper
Author: Arbaaz Laskar
Author-email: arzkar.dev@gmail.com
License: Apache License
Platform: UNKNOWN
Classifier: Programming Language :: Python :: 3
Classifier: License :: OSI Approved :: Apache Software License
Classifier: Operating System :: OS Independent
License-File: LICENSE.txt
Requires-Dist: tqdm (>=4.62.3)
Requires-Dist: colorama (>=0.4.4)
